anusandhan_ml_utils/__init__.py
anusandhan_ml_utils/_modidx.py
anusandhan_ml_utils/card.py
anusandhan_ml_utils/core.py
anusandhan_ml_utils-0.0.2.dist-info/LICENSE
anusandhan_ml_utils-0.0.2.dist-info/METADATA
anusandhan_ml_utils-0.0.2.dist-info/WHEEL
anusandhan_ml_utils-0.0.2.dist-info/entry_points.txt
anusandhan_ml_utils-0.0.2.dist-info/top_level.txt
anusandhan_ml_utils-0.0.2.dist-info/RECORD
